contextbase/__init__.py
contextbase/contextbase.py
contextbase/file.py
contextbase/http_client.py
contextbase/http_error.py
contextbase/http_response.py
contextbase/publish.py
contextbase-1.0.4.dist-info/licenses/LICENSE
contextbase-1.0.4.dist-info/METADATA
contextbase-1.0.4.dist-info/WHEEL
contextbase-1.0.4.dist-info/top_level.txt
contextbase-1.0.4.dist-info/RECORD
